buildingregulariser/__init__.py
buildingregulariser/__version__.py
buildingregulariser/coordinator.py
buildingregulariser/geometry_utils.py
buildingregulariser/neighbor_alignment.py
buildingregulariser/regularization.py
buildingregulariser-0.2.4.dist-info/licenses/LICENSE
buildingregulariser-0.2.4.dist-info/METADATA
buildingregulariser-0.2.4.dist-info/WHEEL
buildingregulariser-0.2.4.dist-info/top_level.txt
buildingregulariser-0.2.4.dist-info/RECORD
