Metadata-Version: 2.4
Name: buildingregulariser
Version: 0.2.4
Summary: A Python library for regularizing building footprints in geospatial data. This library helps clean up and standardize building polygon geometries by aligning edges to principal directions.
Author-email: Nick Wright <nicholas.wright@dpird.wa.gov.au>
License-Expression: MIT
Project-URL: Homepage, https://github.com/DPIRD-DMA/Building-Regulariser
Keywords: building,segmentation,geospatial,geodataframe,geopandas,regularisation,footprint,geometry,regularization,house
Requires-Python: >=3.9
License-File: LICENSE
Requires-Dist: geopandas>=1.0.0
Requires-Dist: numpy>=2.0.0
Dynamic: license-file
